notification/__init__.py
notification/admin.py
notification/api_urls.py
notification/apps.py
notification/models.py
notification/notif_urls.py
notification/tests.py
notification/urls.py
notification/utils.py
notification/views.py
notification/migrations/__init__.py
notification/migrations/__pycache__/__init__.cpython-310.pyc
notification/templates/notification/dep/leave.html
notification/templates/notification/div/leave.html
notification/templates/notification/hr/birthday.html
notification/templates/notification/hr/contract.html
notification/templates/notification/hr/evaluation.html
notification/templates/notification/hr/leave.html
notification/templates/notification/hr/leave_end.html
notification/templates/notification/pr/leave.html
notification/templates/notification/staff/leave.html
notification/templates/notification/vice/leave.html
notification/views/__init__.py
notification/views/api.py
notification/views/notification.py
notification/views/__pycache__/__init__.cpython-310.pyc
notification/views/__pycache__/api.cpython-310.pyc
notification/views/__pycache__/notification.cpython-310.pyc
django_ipghrms_notification-1.2.dist-info/LICENSE
django_ipghrms_notification-1.2.dist-info/METADATA
django_ipghrms_notification-1.2.dist-info/WHEEL
django_ipghrms_notification-1.2.dist-info/top_level.txt
django_ipghrms_notification-1.2.dist-info/RECORD
